combos/__init__.py
combos/combos.py
combos-0.1.0.dist-info/LICENSE
combos-0.1.0.dist-info/METADATA
combos-0.1.0.dist-info/WHEEL
combos-0.1.0.dist-info/top_level.txt
combos-0.1.0.dist-info/RECORD
