Metadata-Version: 2.1
Name: combos
Version: 0.1.0
Summary: Parser combinators for Python.
Author: Nathan Raw
Author-email: naterawdata@gmail.com
License: MIT
License-File: LICENSE
